muninn/__init__.py
muninn/_compat.py
muninn/archive.py
muninn/config.py
muninn/core.py
muninn/enum.py
muninn/exceptions.py
muninn/extension.py
muninn/function.py
muninn/geometry.py
muninn/language.py
muninn/remote.py
muninn/schema.py
muninn/struct.py
muninn/util.py
muninn/visitor.py
muninn/database/__init__.py
muninn/database/base.py
muninn/database/blobgeometry.py
muninn/database/ewkb.py
muninn/database/postgresql.py
muninn/database/sql.py
muninn/database/sqlite.py
muninn/storage/__init__.py
muninn/storage/base.py
muninn/storage/fs.py
muninn/storage/s3.py
muninn/storage/swift.py
muninn/tools/__init__.py
muninn/tools/attach.py
muninn/tools/destroy.py
muninn/tools/export.py
muninn/tools/hash.py
muninn/tools/info.py
muninn/tools/ingest.py
muninn/tools/list_tags.py
muninn/tools/prepare.py
muninn/tools/pull.py
muninn/tools/remove.py
muninn/tools/retrieve.py
muninn/tools/search.py
muninn/tools/strip.py
muninn/tools/summary.py
muninn/tools/sync.py
muninn/tools/tag.py
muninn/tools/untag.py
muninn/tools/update.py
muninn/tools/utils.py
muninn-7.1.0.dist-info/LICENSE
muninn-7.1.0.dist-info/METADATA
muninn-7.1.0.dist-info/WHEEL
muninn-7.1.0.dist-info/entry_points.txt
muninn-7.1.0.dist-info/top_level.txt
muninn-7.1.0.dist-info/RECORD
